[
  {
    "@context": "https://schema.org",
    "@type": "Event",
    "@id": "38699-1762722000-1762729200@aceofpubs.com",
    "name": "Arcade Rave - Underdoggs",
    "startDate": "2025-11-09T21:00:00+05:30",
    "endDate": "2025-11-09T23:00:00+05:30",
    "description": "NOTE: By attending this event, you agree to being filmed at the venue and that content may be used for marketing purposes",
    "url": "https://aceofpubs.com/event/arcade-rave-underdoggs-hebbal-bengaluru-4/",
    "keywords": [
      "Bengaluru"
    ],
    "location": {
      "name": "Underdoggs Hebbal",
      "@type": "Place",
      "address": "Bangalore  Ground Floor  Godrej Centre  Sahakar Nagar  Byatarayanapura   Bengaluru  Karnataka  560092  India"
    },
    "inLanguage": "en"
  }
]