[
  {
    "@context": "https://schema.org",
    "@type": "ScreeningEvent",
    "@id": "547@map-india.org",
    "name": "BN Goswamy: In Memoriam",
    "startDate": "2024-08-14T18:00:00+05:30",
    "endDate": "2024-08-14T18:45:00+05:30",
    "description": "Join us in honouring the birthday of Professor BN Goswamy, a distinguished art historian and a significant supporter of MAP. Although he is no longer with us, his legacy continues to inspire and influence the world of art history.\u00a0\n\nOne of the leading Indian art historians, Professor BN Goswamy was a Professor Emeritus of Art History at the Panjab University, Chandigarh where he also played a pivotal role in the development of the Museum of Fine Arts.\n\nHis work covered a wide range of themes and has significantly influenced thinking on Indian painting. He was especially known for his scholarship on Indian miniatures and courtly painting, in particular Pahari paintings, a subject that he wrote extensively on.\u00a0\n\nEnjoy a selection of films from the series made with Professor BN Goswamy, highlighting his remarkable insights and scholarly journey.",
    "url": "https://map-india.org/map-events/bn-goswamy-in-memoriam/",
    "keywords": [
      "Film Screenings",
      "MAP"
    ],
    "inLanguage": "en",
    "workPresented": {
      "@type": "Movie",
      "name": "BN Goswamy: In Memoriam"
    },
    "image": "https://map-india.org/wp-content/uploads/2024/08/Untitled-design-15.jpg"
  }
]