[
  {
    "name": "Sketchbook Saturday | Abhirama Boloor GK",
    "url": "https://penciljam.com/main/events/sketchbook-saturday-abhirama-boloor-gk/",
    "startDate": "2026-05-30T14:00:00+05:30",
    "endDate": "2026-05-30T15:00:00+05:30",
    "description": "\nSketchbook Saturday\nSketchbooks are a private, and intimate space for artists to think, experiment, and try new ways of designing or creating art. Sketchbook Saturday is a bi-monthly event that sees artists from the Penciljam community sharing their Sketchbooks and creative process.\nAbout the Artist\nAbhirama is a Bengaluru-based concept artist working across animated feature films and shows. His practice focuses on visual storytelling, world-building and observational drawing, often inspired by everyday spaces, travel and lived experiences. Alongside his professional work in animation, he explores independent storytelling through film, games and personal visual studies. Through drawing and documentation, he is interested in understanding places, people and narratives, using observation as a way to expand his visual language and creative perspective.\n\nAbhirama\u2019s website &amp; IG profile |\nHow to attend this session\n\n \tPlease register here to attend this session.\n \tThe session starts at 2pm on Saturday, at Blr Design Centre\n \tReach the venue 15mins before 2pm.\n\nIn Collaboration with Blrdesign Centre\nThe BLR Design Centre is a collaborative workroom run by Mod Foundation focused on transforming urban living environments through architectural partnerships, cultural dialogue, and design-driven solutions.",
    "location": {
      "@type": "Place",
      "name": "https://maps.app.goo.gl/ZaAPjcntjiuiKLeg6",
      "url": "https://maps.app.goo.gl/ZaAPjcntjiuiKLeg6"
    }
  },
  {
    "name": "Penciljam Bengaluru at MAP",
    "url": "https://penciljam.com/main/events/penciljam-bengaluru-at-map-2/",
    "startDate": "2026-05-31T10:30:00+05:30",
    "endDate": "2026-05-31T13:00:00+05:30",
    "description": "\n\nWe are drawing at the Museum of Art and Photography this Sunday.\n\nThe Museum of Art &amp; Photography (MAP), located in the heart of Bengaluru, is dedicated to making art accessible and engaging for all. Visit their website to see the current exhibits: https://map-india.org/\n\nWe are delighted to continue to partner with MAP who has made the space available for this session from 10:30am to 1pm. A quite day to immerse ourselves at the Museum.\nHow to join this session\nYou don't need artistic skill to participate in this event - just boundless curiosity and a love for drawing. To connect with other participants, please use our Discord community app. (Link to the Discord Community Here.)\n\nPlease register here to attend this event. Please arrive at the museum before 10:30 am to join the briefing &amp; introduction for this session at the Museum.\nOnce you arrive at MAP\n\n \tInform the front desk that you are there for Penciljam,\n \tConfirm your name against the RSVP list, you can also register on the spot for this event\n \tLeave your bag in the lockers at the basement level.\n \tYou can carry an A4/A5 or smaller sketchbook and portable dry material kit to draw within.\n \tChoose a spot you'd like to sketch and get comfortable - be mindful of not blocking the path of visitors to the museum.\n\nThings to carry for this session:\n\n \tA sketchbook/paper (A4/A5 or smaller sketchbook)\n \tArt materials of your choice - Pencils or any dry medium. (within the museum we cannot use wet media like paints. Only non-messy dry media is allowed)\n\nHow to get there\nThis building is opposite the Government Museum.\nFollow the location map provided\nClosest metro station: Cubbon Park Metro station (900m from MAP)",
    "location": {
      "@type": "Place",
      "name": "MAP",
      "url": "https://maps.app.goo.gl/jFaLsPyKCnYKmkhN7"
    }
  }
]