[
  {
    "id": "buzz.venn:4537",
    "name": "Women\u2019s Ultimate Frisbee Night",
    "image": "https://api.venn.buzz/rails/active_storage/blobs/redirect/eyJfcmFpbHMiOnsiZGF0YSI6MjA4OTIsInB1ciI6ImJsb2JfaWQifX0=--c5cf25f749f99371f13e91ef08b62f5d9905d082/42acdd6f-e0e0-45f2-b1e4-3d4a7ab5f159",
    "location": {
      "name": "South United Football Club, Ulsoor",
      "address": "South United Football Club, Ulsoor Bangalore"
    },
    "url": "https://app.venn.buzz/social_experience/4537",
    "sameAs": null,
    "startDate": "2025-05-21T19:15:00+0530",
    "endDate": "2025-05-21T21:15:00+05:30",
    "description": "A women-only intro to Ultimate Frisbee\u2014think football meets basketball, but chiller. Fast, fun, and no experience needed"
  },
  {
    "id": "buzz.venn:4538",
    "name": "Atoms to Applications",
    "image": "https://api.venn.buzz/rails/active_storage/blobs/redirect/eyJfcmFpbHMiOnsiZGF0YSI6MjA5MjUsInB1ciI6ImJsb2JfaWQifX0=--ede38fb014858cfff26ecc6c26767bb7e97562a5/1859426a-8a8d-4453-8c48-11b275bf56e5",
    "location": {
      "name": "Cafe Azzure, MG Road",
      "address": "Cafe Azzure, MG Road Bangalore"
    },
    "url": "https://app.venn.buzz/social_experience/4538",
    "sameAs": "https://www.pintofscience.in/event-details/atoms-to-applications-1",
    "startDate": "2025-05-20T18:00:00+0530",
    "endDate": "2025-05-20T20:00:00+05:30",
    "description": "Atoms to Applications traces the journey from atomic theory to real-world tech blending deep science with practical insights by Prof. Michael Rajamathi from St. Joseph's University & Gadhadar Reddy, CEO of Nopo Nanotechnologies"
  },
  {
    "id": "buzz.venn:4539",
    "name": "Highs, Lows & Happy Hours: Inside the Human Brain",
    "image": "https://api.venn.buzz/rails/active_storage/blobs/redirect/eyJfcmFpbHMiOnsiZGF0YSI6MjA5MjcsInB1ciI6ImJsb2JfaWQifX0=--0748d32ca2c85bf7273b951e293964b95a0fdd1e/995f0f7c-6d8e-4ff8-8033-5181b047b101",
    "location": {
      "name": "SkyDeck by Sherlock's, Ashoknagar",
      "address": "SkyDeck by Sherlock's, Ashoknagar Bangalore"
    },
    "url": "https://app.venn.buzz/social_experience/4539",
    "sameAs": "https://www.pintofscience.in/event-details/highs-lows-happy-hours",
    "startDate": "2025-05-20T18:00:00+0530",
    "endDate": "2025-05-20T20:00:00+05:30",
    "description": "From brain cells to beer goggles \u2014 Neuroscientist Reeteka Sud and Doctor Jayant Mahadevan (NIMHANS) explore how early development and genetics shape psychiatric illness and alcohol use, and what science is doing about it"
  },
  {
    "id": "buzz.venn:4540",
    "name": "Tuesday Tidbits",
    "image": "https://api.venn.buzz/rails/active_storage/blobs/redirect/eyJfcmFpbHMiOnsiZGF0YSI6MjA5MjksInB1ciI6ImJsb2JfaWQifX0=--342937cd715f5e9d4cb53a0e14c09b4aaab3be8e/dd111d00-a7bb-4454-b91e-4f012bffeaf5",
    "location": {
      "name": "Museum of Art & Photography, Kasturba Road",
      "address": "Museum of Art & Photography, Kasturba Road Bangalore"
    },
    "url": "https://app.venn.buzz/social_experience/4540",
    "sameAs": "https://map-india.org/map-events/tuesday-tidbits-11/",
    "startDate": "2025-05-20T17:00:00+0530",
    "endDate": "2025-05-20T19:00:00+05:30",
    "description": "Why is Venus fragmented? What stories lie in sketches? Aayati Sengupta decodes museum mysteries with art, insight, and career cues at Tuesday Tidbits."
  },
  {
    "id": "buzz.venn:4541",
    "name": "Signs from the Sky: Decoding Indus Valley Seals",
    "image": "https://api.venn.buzz/rails/active_storage/blobs/redirect/eyJfcmFpbHMiOnsiZGF0YSI6MjA5MzEsInB1ciI6ImJsb2JfaWQifX0=--fb060954dfb758e234da8c9e2cad9d99c5751f0d/5f3e90f2-7319-4f42-9481-b812e18d97c8",
    "location": {
      "name": "BIC, Domlur",
      "address": "BIC, Domlur Bangalore"
    },
    "url": "https://app.venn.buzz/social_experience/4541",
    "sameAs": "https://bangaloreinternationalcentre.org/event/signs-from-the-sky/",
    "startDate": "2025-05-20T18:30:00+0530",
    "endDate": "2025-05-20T20:30:00+05:30",
    "description": "This deep dive into Indus Valley seals reconsiders ancient symbols with fresh eyes\u2014uncovering cultural nuance and layered meanings buried across millennia"
  },
  {
    "id": "buzz.venn:4542",
    "name": "Bangalore Ultimate: Beginners Ultimate Frisbee 101",
    "image": "https://api.venn.buzz/rails/active_storage/blobs/redirect/eyJfcmFpbHMiOnsiZGF0YSI6MjA5MzMsInB1ciI6ImJsb2JfaWQifX0=--86487e1fc5627232ddf47bc2c41ab1395b8566a9/fe40f597-a4f9-4323-b30e-29333825b982",
    "location": {
      "name": "Rush Arena, Cooke Town",
      "address": "Rush Arena, Cooke Town Bangalore"
    },
    "url": "https://app.venn.buzz/social_experience/4542",
    "sameAs": null,
    "startDate": "2025-05-22T19:15:00+0530",
    "endDate": "2025-05-22T21:15:00+05:30",
    "description": "A beginner-friendly plunge into ultimate frisbee\u2014this session fuses speed, strategy, and camaraderie for a dynamic, high-energy game that\u2019s as social as it is athletic"
  }
]