[
  {
    "id": "buzz.venn:3837",
    "name": "How to Maintain Your Manual Brewers? ",
    "image": "https://api.venn.buzz/rails/active_storage/blobs/redirect/eyJfcmFpbHMiOnsiZGF0YSI6MTc0MTQsInB1ciI6ImJsb2JfaWQifX0=--89692846f609e2c255babeb6ee65cf033c492152/2b205f0b-ab2b-4cf9-92ba-846fb748ed67",
    "location": {
      "name": "Something's Brewing, Indiranagar",
      "address": "Something's Brewing, Indiranagar Bangalore"
    },
    "url": "https://app.venn.buzz/social_experience/3837",
    "sameAs": null,
    "startDate": "2025-03-07T16:00:00+0530",
    "endDate": "2025-03-07T18:00:00+05:30",
    "description": "If you want to learn to maintain & best clean your manual brewers to keep them performing at their best, Something's Brewing are hosting"
  },
  {
    "id": "buzz.venn:3838",
    "name": "One Day",
    "image": "https://api.venn.buzz/rails/active_storage/blobs/redirect/eyJfcmFpbHMiOnsiZGF0YSI6MTc0MTYsInB1ciI6ImJsb2JfaWQifX0=--005176f9bf85b335ae807a5f183215505d78e2b2/911931fc-d0f9-4354-a389-0a1920d17fe5",
    "location": {
      "name": "Chapter 6, Koramangala",
      "address": "Chapter 6, Koramangala Bangalore"
    },
    "url": "https://app.venn.buzz/social_experience/3838",
    "sameAs": null,
    "startDate": "2025-03-07T19:00:00+0530",
    "endDate": "2025-03-07T21:00:00+05:30",
    "description": "Open air screening of director Lone Scherfig's romantic drama"
  },
  {
    "id": "buzz.venn:3839",
    "name": "SIS x Banana Sports Women's Day Pickleball Celebration",
    "image": "https://api.venn.buzz/rails/active_storage/blobs/redirect/eyJfcmFpbHMiOnsiZGF0YSI6MTc0MTgsInB1ciI6ImJsb2JfaWQifX0=--b43e113d7ce092e84009a07fa3ac11a252d3bebb/5f52b8f7-9ea9-409f-8ccd-2e5a1de97926",
    "location": {
      "name": "Banana Sports, Sarjapur Road",
      "address": "Banana Sports, Sarjapur Road Bangalore"
    },
    "url": "https://app.venn.buzz/social_experience/3839",
    "sameAs": null,
    "startDate": "2025-03-08T17:00:00+0530",
    "endDate": "2025-03-08T19:00:00+05:30",
    "description": "For ladies who're interested in an exciting Pickleball session with your girls this Women's Day, SIS X Banana Sports are hosting "
  },
  {
    "id": "buzz.venn:3840",
    "name": "ChessCafe: A Chess Meetup with a Twist",
    "image": "https://api.venn.buzz/rails/active_storage/blobs/redirect/eyJfcmFpbHMiOnsiZGF0YSI6MTc0MjAsInB1ciI6ImJsb2JfaWQifX0=--e9dd9870df652e9a8fa68c77ad9c1df9254560a3/63355380-15cb-494e-9bde-71cc72354b37",
    "location": {
      "name": "Starbucks, Jayanagar",
      "address": "Starbucks, Jayanagar Bangalore"
    },
    "url": "https://app.venn.buzz/social_experience/3840",
    "sameAs": null,
    "startDate": "2025-03-08T10:00:00+0530",
    "endDate": "2025-03-08T12:00:00+05:30",
    "description": "If you're interested in a chess meetup with game variations like Casual Standard chess, Hand & brain Chess & more, BLR Chess Club are hosting"
  },
  {
    "id": "buzz.venn:3841",
    "name": "Paper, Language, and Us",
    "image": "https://api.venn.buzz/rails/active_storage/blobs/redirect/eyJfcmFpbHMiOnsiZGF0YSI6MTc0MjIsInB1ciI6ImJsb2JfaWQifX0=--db84bba7786011d28bf6a2d44e76b33ce86b53ff/b47be1e4-88bd-47ab-b235-dd7f742eb0f2",
    "location": {
      "name": "Museum of Art & Photography, Kasturba Road",
      "address": "Museum of Art & Photography, Kasturba Road Bangalore"
    },
    "url": "https://app.venn.buzz/social_experience/3841",
    "sameAs": null,
    "startDate": "2025-03-08T18:00:00+0530",
    "endDate": "2025-03-08T20:00:00+05:30",
    "description": "A talk exploring the new exhibit 'We don\u2019t end at our edges'  which uses paper to 'paint' letters, with artist Ravikumar Kashi "
  },
  {
    "id": "buzz.venn:3848",
    "name": "Women\u2019s day workout",
    "image": "https://api.venn.buzz/rails/active_storage/blobs/redirect/eyJfcmFpbHMiOnsiZGF0YSI6MTc0NjQsInB1ciI6ImJsb2JfaWQifX0=--d79c70b95502ddd41e942aa8623974373f49589f/fa8cf38b-825e-4a42-9362-cef494f4d077",
    "location": {
      "name": "Tagda Raho, Ulsoor",
      "address": "Tagda Raho, Ulsoor Bangalore"
    },
    "url": "https://app.venn.buzz/social_experience/3848",
    "sameAs": null,
    "startDate": "2025-03-07T19:00:00+0530",
    "endDate": "2025-03-07T21:00:00+05:30",
    "description": "For ladies who're interested to explore strength & mobility using Indian clubs & maces with a +1, Tagda Raho are hosting "
  },
  {
    "id": "buzz.venn:3849",
    "name": "Artist-led Guided Walk",
    "image": "https://api.venn.buzz/rails/active_storage/blobs/redirect/eyJfcmFpbHMiOnsiZGF0YSI6MTc0NjYsInB1ciI6ImJsb2JfaWQifX0=--479ed570e1d61d87f5c5a7139fae46539e9e8651/bf9211a4-4dea-4ea7-b908-81746c8fdaf8",
    "location": {
      "name": "Museum of Art & Photography, Kasturba Road",
      "address": "Museum of Art & Photography, Kasturba Road Bangalore"
    },
    "url": "https://app.venn.buzz/social_experience/3849",
    "sameAs": null,
    "startDate": "2025-03-08T11:30:00+0530",
    "endDate": "2025-03-08T13:30:00+05:30",
    "description": "A guided walk in Kannada & English by artist Ravikumar Kashi of his exhibition, 'We don't end at our edges'"
  },
  {
    "id": "buzz.venn:3850",
    "name": "Succulent Garden Workshop",
    "image": "https://api.venn.buzz/rails/active_storage/blobs/redirect/eyJfcmFpbHMiOnsiZGF0YSI6MTc0NjgsInB1ciI6ImJsb2JfaWQifX0=--7ffa7a794de32f97cf052c3e3dc88475f322555d/264f1835-bb52-4719-ac72-717cd8ea043c",
    "location": {
      "name": "Urth - Flower and Plant shop, Indiranagar",
      "address": "Urth - Flower and Plant shop, Indiranagar Bangalore"
    },
    "url": "https://app.venn.buzz/social_experience/3850",
    "sameAs": null,
    "startDate": "2025-03-08T16:00:00+0530",
    "endDate": "2025-03-08T18:00:00+05:30",
    "description": "If you're interested in a workshop to design & create a beautiful miniature garden, plant enthusiast Ankita is hosting"
  },
  {
    "id": "buzz.venn:3851",
    "name": "The Devil Wears Prada",
    "image": "https://api.venn.buzz/rails/active_storage/blobs/redirect/eyJfcmFpbHMiOnsiZGF0YSI6MTc0NzAsInB1ciI6ImJsb2JfaWQifX0=--d39bd13634afa654429f06291d5a26909d801d18/a1736b1b-8c5e-4d6c-b725-31fbc4da72cd",
    "location": {
      "name": "Forum, South Bangalore",
      "address": "Forum, South Bangalore Bangalore"
    },
    "url": "https://app.venn.buzz/social_experience/3851",
    "sameAs": null,
    "startDate": "2025-03-08T19:00:00+0530",
    "endDate": "2025-03-08T21:00:00+05:30",
    "description": "Open air screening of director David Frankel's comedy drama "
  },
  {
    "id": "buzz.venn:3852",
    "name": "Chess Connect Triathlon",
    "image": "https://api.venn.buzz/rails/active_storage/blobs/redirect/eyJfcmFpbHMiOnsiZGF0YSI6MTc0NzIsInB1ciI6ImJsb2JfaWQifX0=--235fad91bfbfc82d098cd50aa41602d81a54062a/764963e6-239b-4d9a-aa29-986c975f60a4",
    "location": {
      "name": "RMZ Infinity, Bennigana Halli",
      "address": "RMZ Infinity, Bennigana Halli Bangalore"
    },
    "url": "https://app.venn.buzz/social_experience/3852",
    "sameAs": null,
    "startDate": "2025-03-09T10:00:00+0530",
    "endDate": "2025-03-09T12:00:00+05:30",
    "description": "If you're interested in a chess meet-up in 3 formats: Blitz, Freestyle Chess & Rapid, BLR Chess Club are hosting"
  },
  {
    "id": "buzz.venn:3853",
    "name": "The Grape Canvas",
    "image": "https://api.venn.buzz/rails/active_storage/blobs/redirect/eyJfcmFpbHMiOnsiZGF0YSI6MTc0NzQsInB1ciI6ImJsb2JfaWQifX0=--316d777fda5f5a7e1e783062cd1b7e057e283490/b6677026-1b3d-4547-a4cb-5b55c0eda728",
    "location": {
      "name": "La Gioia, Indiranagar",
      "address": "La Gioia, Indiranagar Bangalore"
    },
    "url": "https://app.venn.buzz/social_experience/3853",
    "sameAs": null,
    "startDate": "2025-03-09T16:00:00+0530",
    "endDate": "2025-03-09T18:00:00+05:30",
    "description": "If you want to learn about wine labels from around the world & design one of your own to win a prize, WIne In A Million are hosting"
  },
  {
    "id": "buzz.venn:3854",
    "name": "Bhuri Bhoj",
    "image": "https://api.venn.buzz/rails/active_storage/blobs/redirect/eyJfcmFpbHMiOnsiZGF0YSI6MTc1MjEsInB1ciI6ImJsb2JfaWQifX0=--1e1ad8836e586e8bcf0bdcbabfa94e44d6a1cb5f/91496fc8-87f2-4766-9a2e-a9189a6e465f",
    "location": {
      "name": "Courtyard by Marriott",
      "address": "Courtyard by Marriott Bangalore"
    },
    "url": "https://app.venn.buzz/social_experience/3854",
    "sameAs": "https://drive.google.com/file/d/1oIVKwxtk8fSwd7V1Fu2gn0iQNf26LIaQ/view?usp=sharing",
    "startDate": "2025-03-07T19:00:00+0530",
    "endDate": "2025-03-07T21:00:00+05:30",
    "description": "If you want to indulge in a contemporary reinpretation of Bengali flavours, Chef Ananya Banerjee is hosting"
  },
  {
    "id": "buzz.venn:3855",
    "name": "A\u1e45gah\u0101ra\u1e25",
    "image": "https://api.venn.buzz/rails/active_storage/blobs/redirect/eyJfcmFpbHMiOnsiZGF0YSI6MTc1MjMsInB1ciI6ImJsb2JfaWQifX0=--d43860325701c23621da4392a2090999b26f25d3/e2711175-8907-4292-bb64-fee7ed5abfed",
    "location": {
      "name": "Courtyard Koota",
      "address": "Courtyard Koota Bangalore"
    },
    "url": "https://app.venn.buzz/social_experience/3855",
    "sameAs": "https://courtyardkoota.com/events/a%E1%B9%85gahara%E1%B8%A5/",
    "startDate": "2025-03-07T18:30:00+0530",
    "endDate": "2025-03-07T20:30:00+05:30",
    "description": "If you like Indian classical dance form of Odissi, dancers Anoushka Rahman & Pavithra Reddy are performing"
  },
  {
    "id": "buzz.venn:3856",
    "name": "Coorg Dinner",
    "image": "https://api.venn.buzz/rails/active_storage/blobs/redirect/eyJfcmFpbHMiOnsiZGF0YSI6MTc1MjUsInB1ciI6ImJsb2JfaWQifX0=--1d72ad1e07a85ba32ecef5989b374c8960715b14/cb29865e-e05c-498a-81b9-dd82e706033a",
    "location": {
      "name": "Trippy Goat, Cunningham Road",
      "address": "Trippy Goat, Cunningham Road Bangalore"
    },
    "url": "https://app.venn.buzz/social_experience/3856",
    "sameAs": "https://pages.razorpay.com/pl_Pyl6F6j6cK5t4J/view",
    "startDate": "2025-03-07T19:00:00+0530",
    "endDate": "2025-03-07T21:00:00+05:30",
    "description": "If you want to enjoy authentic Coorgi cuisine, Chef Sitara Cariappa's family X Trippy Goat are hosting"
  },
  {
    "id": "buzz.venn:3857",
    "name": "Women in Art & Performance",
    "image": "https://api.venn.buzz/rails/active_storage/blobs/redirect/eyJfcmFpbHMiOnsiZGF0YSI6MTc1MjcsInB1ciI6ImJsb2JfaWQifX0=--d4f37232a11207dbcf4d10907d9c15799e2a245a/a21aab0c-c135-40a0-b99b-030dce5911fb",
    "location": {
      "name": "Medai- The Stage",
      "address": "Medai- The Stage Bangalore"
    },
    "url": "https://app.venn.buzz/social_experience/3857",
    "sameAs": "https://www.instagram.com/p/DGx8HwByTSB/?igsh=MzRlODBiNWFlZA%3D%3D",
    "startDate": "2025-03-07T18:30:00+0530",
    "endDate": "2025-03-07T20:30:00+05:30",
    "description": "If you're interested in a creative evening with performances, poetry, movies & more celebrating women, Ektas Gatherings & Medai are hosting"
  },
  {
    "id": "buzz.venn:3858",
    "name": "Tribute to Midnight Diner: Tokyo Stories",
    "image": "https://api.venn.buzz/rails/active_storage/blobs/redirect/eyJfcmFpbHMiOnsiZGF0YSI6MTc1MjksInB1ciI6ImJsb2JfaWQifX0=--3bb16388623d2a2a177944e4f85eddc6c220d137/db3a0d5e-ce92-4918-8f7a-fd5e23b9466a",
    "location": {
      "name": "Bento Bento",
      "address": "Bento Bento Bangalore"
    },
    "url": "https://app.venn.buzz/social_experience/3858",
    "sameAs": "https://urbanaut.app/spot/midnight-diner-tokyo-stories",
    "startDate": "2025-03-07T19:00:00+0530",
    "endDate": "2025-03-07T21:00:00+05:30",
    "description": "A heartfelt culinary homage to the beloved series 'Midnight Diner: Tokyo Stories' by Chef Anumitra at Bento Bento "
  },
  {
    "id": "buzz.venn:3859",
    "name": "Women on Record",
    "image": "https://api.venn.buzz/rails/active_storage/blobs/redirect/eyJfcmFpbHMiOnsiZGF0YSI6MTc1MzEsInB1ciI6ImJsb2JfaWQifX0=--5c5c7d8b6becc3c7ec61b74329fa9c6341605fef/aa09e15d-a390-4862-afb3-0762e2b67915",
    "location": {
      "name": "BIC, Domlur",
      "address": "BIC, Domlur Bangalore"
    },
    "url": "https://app.venn.buzz/social_experience/3859",
    "sameAs": null,
    "startDate": "2025-03-07T19:00:00+0530",
    "endDate": "2025-03-07T21:00:00+05:30",
    "description": "A captivating multimedia performance bringing to life stories of the 20th century Baijis- \u2014the pioneering women of India\u2019s gramophone era"
  },
  {
    "id": "buzz.venn:3860",
    "name": "Garment Kelsa: Women & Work",
    "image": "https://api.venn.buzz/rails/active_storage/blobs/redirect/eyJfcmFpbHMiOnsiZGF0YSI6MTc1MzMsInB1ciI6ImJsb2JfaWQifX0=--d0a6387c59c2a81666be49ff04ca480e46ec6f29/f2b0e569-cb8f-4862-b268-dae2bc950886",
    "location": {
      "name": "Lagori Collective, Cooke Town",
      "address": "Lagori Collective, Cooke Town Bangalore"
    },
    "url": "https://app.venn.buzz/social_experience/3860",
    "sameAs": null,
    "startDate": "2025-03-07T16:00:00+0530",
    "endDate": "2025-03-07T18:00:00+05:30",
    "description": "Screening of a  documentary film following the lives of 5 women & how the garment industry shapes women's lives, homes & futures "
  },
  {
    "id": "buzz.venn:3861",
    "name": "Sip & Solve Trivia Night ",
    "image": "https://api.venn.buzz/rails/active_storage/blobs/redirect/eyJfcmFpbHMiOnsiZGF0YSI6MTc1MzUsInB1ciI6ImJsb2JfaWQifX0=--0ead07d5047c1750ac9d950170eb0e54c5adeb43/5a9a9076-9824-4611-8a45-ce56596425fc",
    "location": {
      "name": "Biergarten Brewery & Kitchen, Koramangala",
      "address": "Biergarten Brewery & Kitchen, Koramangala Bangalore"
    },
    "url": "https://app.venn.buzz/social_experience/3861",
    "sameAs": null,
    "startDate": "2025-03-07T18:00:00+0530",
    "endDate": "2025-03-07T20:00:00+05:30",
    "description": "For ladies who enjoy Quizzes & want to learn bouquet making while sipping on beer this Women's day, AnitaB Org India X Bier Garten are hosting"
  },
  {
    "id": "buzz.venn:3862",
    "name": "DIY Repair Day!",
    "image": "https://api.venn.buzz/rails/active_storage/blobs/redirect/eyJfcmFpbHMiOnsiZGF0YSI6MTc1MzcsInB1ciI6ImJsb2JfaWQifX0=--b237b44c8fda1be3a6f0469f1239ab8a3540d759/3872888f-def5-4fe7-961b-fb45c0cdbc58",
    "location": {
      "name": "Paper Crane Lab",
      "address": "Paper Crane Lab Bangalore"
    },
    "url": "https://app.venn.buzz/social_experience/3862",
    "sameAs": null,
    "startDate": "2025-03-08T11:00:00+0530",
    "endDate": "2025-03-08T13:00:00+05:30",
    "description": "If you've always wanted to repair things which are broken around your house or learn to fix a button with some help, PCL are hosting"
  },
  {
    "id": "buzz.venn:3863",
    "name": "Come Listen to Norah with Me ",
    "image": "https://api.venn.buzz/rails/active_storage/blobs/redirect/eyJfcmFpbHMiOnsiZGF0YSI6MTc1MzksInB1ciI6ImJsb2JfaWQifX0=--b74dc905212187a1f965347b9ac71dbc3d2ab798/278bf078-76f9-46ca-b78b-ce91e0eb79db",
    "location": {
      "name": "Ram\u2019s Musique Experience, MG Road",
      "address": "Ram\u2019s Musique Experience, MG Road Bangalore"
    },
    "url": "https://app.venn.buzz/social_experience/3863",
    "sameAs": null,
    "startDate": "2025-03-08T16:30:00+0530",
    "endDate": "2025-03-08T18:30:00+05:30",
    "description": "If you're interested in a Vinyl listening session of Norah Jones's album 'Come Away With Me' moderated by Goutham, Ram's Musique are hosting"
  },
  {
    "id": "buzz.venn:3864",
    "name": "A Frazer Town Iftaar Experience with Zafir",
    "image": "https://api.venn.buzz/rails/active_storage/blobs/redirect/eyJfcmFpbHMiOnsiZGF0YSI6MTc1NDEsInB1ciI6ImJsb2JfaWQifX0=--2163649421a7a21dcb223c81365224d6d02e7d3a/2a64a417-35db-45d0-b4cd-1e397e3d99ca",
    "location": {
      "name": "Chichaba's Taj, Frazer Town",
      "address": "Chichaba's Taj, Frazer Town Bangalore"
    },
    "url": "https://app.venn.buzz/social_experience/3864",
    "sameAs": null,
    "startDate": "2025-03-08T17:45:00+0530",
    "endDate": "2025-03-08T19:45:00+05:30",
    "description": "If you want to celebrate the spirit of Ramadan with a 6 course Iftaar table expereince, curator Zafir Syed is hosting"
  },
  {
    "id": "buzz.venn:3865",
    "name": "Yeh Jawaani Hai Deewani",
    "image": "https://api.venn.buzz/rails/active_storage/blobs/redirect/eyJfcmFpbHMiOnsiZGF0YSI6MTc1NDMsInB1ciI6ImJsb2JfaWQifX0=--3f0db71efc1a5a5867ae30d8fa8ad55a17770078/5abd793f-0e48-484c-81c6-4d6d0ebc66a4",
    "location": {
      "name": "1MG, Lido Mall, Halasuru",
      "address": "1MG, Lido Mall, Halasuru Bangalore"
    },
    "url": "https://app.venn.buzz/social_experience/3865",
    "sameAs": null,
    "startDate": "2025-03-08T19:00:00+0530",
    "endDate": "2025-03-08T21:00:00+05:30",
    "description": "Open air screening of director Ayan Mukerji's coming-of-age romantic comedy"
  },
  {
    "id": "buzz.venn:3866",
    "name": "The RE - Market (Reduce, Reuse and Recycle) ",
    "image": "https://api.venn.buzz/rails/active_storage/blobs/redirect/eyJfcmFpbHMiOnsiZGF0YSI6MTc1NDUsInB1ciI6ImJsb2JfaWQifX0=--95eee8bbbb7119d5bcf1633665a438cee1085f80/96d86af6-b9da-4407-b730-1c64f4f0987c",
    "location": {
      "name": "Bangalore Creative Circus, Yeshwanthapur",
      "address": "Bangalore Creative Circus, Yeshwanthapur Bangalore"
    },
    "url": "https://app.venn.buzz/social_experience/3866",
    "sameAs": null,
    "startDate": "2025-03-09T11:00:00+0530",
    "endDate": "2025-03-09T13:00:00+05:30",
    "description": "Shop for preloved fashion, enjoy live music, farm-to-table food & fun workshops & a place to Drop off old clothes & dry waste at BCC"
  },
  {
    "id": "buzz.venn:3867",
    "name": "Her Sanctuary : The Embodied Retreat",
    "image": "https://api.venn.buzz/rails/active_storage/blobs/redirect/eyJfcmFpbHMiOnsiZGF0YSI6MTc1NDcsInB1ciI6ImJsb2JfaWQifX0=--8c4bf0a92b35d98a4d2f91426f375bdb8b40a5aa/24b06e1d-a869-4d88-a27e-717c930b8015",
    "location": {
      "name": "Copper + Cloves Studio",
      "address": "Copper + Cloves Studio Bangalore"
    },
    "url": "https://app.venn.buzz/social_experience/3867",
    "sameAs": null,
    "startDate": "2025-03-09T15:00:00+0530",
    "endDate": "2025-03-09T17:00:00+05:30",
    "description": "If you're interested in a transformative experience of self- awareness, healing & reconnection, Instructors Franziska & Sanjana are hosting"
  }
]