[
  {
    "id": "buzz.venn:3483",
    "name": "The Stage at ParTTwo presents: Voctronica ",
    "image": "https://api.venn.buzz/rails/active_storage/blobs/redirect/eyJfcmFpbHMiOnsiZGF0YSI6MTU4MzYsInB1ciI6ImJsb2JfaWQifX0=--ea4cf7ccec932ee55e64dcadc37839309ed21684/2d34fd13-3386-48c1-8c43-8fe8da3b555e",
    "location": {
      "name": "The Biere Club",
      "address": "The Biere Club Bangalore"
    },
    "url": "https://app.venn.buzz/social_experience/3483",
    "sameAs": null,
    "startDate": "2025-01-29T19:00:00+0530",
    "endDate": "2025-01-29T21:00:00+05:30",
    "description": "If you want to listen to India\u2019s first all-vocal band 'Voctronica' perform, ParTTwo are hosting"
  },
  {
    "id": "buzz.venn:3484",
    "name": "3D-Printed Cookie Cutters",
    "image": "https://api.venn.buzz/rails/active_storage/blobs/redirect/eyJfcmFpbHMiOnsiZGF0YSI6MTU4NDQsInB1ciI6ImJsb2JfaWQifX0=--203775d350cad22f11c979820988ea8ab8102c7c/e3e0d1c4-320e-42e0-867f-7f1902f7d17d",
    "location": {
      "name": "Paper Crane Lab",
      "address": "Paper Crane Lab Bangalore"
    },
    "url": "https://app.venn.buzz/social_experience/3484",
    "sameAs": "https://www.instagram.com/p/DFViQ2QylVy/",
    "startDate": "2025-01-29T19:00:00+0530",
    "endDate": "2025-01-29T21:00:00+05:30",
    "description": "If you're interested in a beginner-friendly workshop to design & create custom cookie cutters, PCL are hosting"
  },
  {
    "id": "buzz.venn:3485",
    "name": "International Puzzle Day",
    "image": "https://api.venn.buzz/rails/active_storage/blobs/redirect/eyJfcmFpbHMiOnsiZGF0YSI6MTU4NDYsInB1ciI6ImJsb2JfaWQifX0=--dc4b6fc42e4ee05b11f31e14108827349912fd6e/08f9f5ac-79f4-4e86-bf5a-89b5c51b7435",
    "location": {
      "name": "Underline Center, Indiranagar",
      "address": "Underline Center, Indiranagar Bangalore"
    },
    "url": "https://app.venn.buzz/social_experience/3485",
    "sameAs": "https://insider.in/international-puzzle-day-with-playful-pursuits-jigsaw-puzzle-association-of-india-jan29-2025/event",
    "startDate": "2025-01-29T18:00:00+0530",
    "endDate": "2025-01-29T20:00:00+05:30",
    "description": "If you want to participate in a global puzzling event to celebrate International Puzzle Day, Playful Pursuits & JPAI are hosting "
  },
  {
    "id": "buzz.venn:3486",
    "name": "Short Film Festival",
    "image": "https://api.venn.buzz/rails/active_storage/blobs/redirect/eyJfcmFpbHMiOnsiZGF0YSI6MTU4NDgsInB1ciI6ImJsb2JfaWQifX0=--4c1486928b8458b24a76857719e76c1d578d5629/39ac572f-4207-40d7-ab4f-9fcc54ad45a0",
    "location": {
      "name": "J N Tata Auditorium, Malleswaram",
      "address": "J N Tata Auditorium, Malleswaram Bangalore"
    },
    "url": "https://app.venn.buzz/social_experience/3486",
    "sameAs": "https://www.instagram.com/p/DFNQLhVIaye/",
    "startDate": "2025-01-29T12:00:00+0530",
    "endDate": "2025-01-29T14:00:00+05:30",
    "description": "If you want to watch a series of short films, Bengaluru International Short Film Festival are hosting"
  },
  {
    "id": "buzz.venn:3487",
    "name": "Freewheelin' Meet-up",
    "image": "https://api.venn.buzz/rails/active_storage/blobs/redirect/eyJfcmFpbHMiOnsiZGF0YSI6MTU4NTAsInB1ciI6ImJsb2JfaWQifX0=--7da2d9c2959fe8a5368d70ab56fc576f2c7538e4/fa0c2f8d-efbc-49cd-b1c2-48e6680caea4",
    "location": {
      "name": "Pedal In Tandem",
      "address": "Pedal In Tandem Bangalore"
    },
    "url": "https://app.venn.buzz/social_experience/3487",
    "sameAs": "https://www.pedalintandem.com/experiences/thePITStop/freewheeling",
    "startDate": "2025-01-29T19:30:00+0530",
    "endDate": "2025-01-29T21:30:00+05:30",
    "description": "If you want to savor the sounds, smell & tastes of Bangalore with a community of cycling enthusiasts: Pedal In Tandem are hosting"
  },
  {
    "id": "buzz.venn:3488",
    "name": "Bar Takeover by Ishrat Kaur",
    "image": "https://api.venn.buzz/rails/active_storage/blobs/redirect/eyJfcmFpbHMiOnsiZGF0YSI6MTU4NTIsInB1ciI6ImJsb2JfaWQifX0=--e79307a2f1a99c7e1362a1c0204da37dbf00b45a/bade50e4-7380-4588-89b7-d21e876b5a19",
    "location": {
      "name": "The Drawing Room (Smoke House Deli), Indiranagar",
      "address": "The Drawing Room (Smoke House Deli), Indiranagar Bangalore"
    },
    "url": "https://app.venn.buzz/social_experience/3488",
    "sameAs": "https://insider.in/the-gin-odyssey-x-bacardi-bar-takeover-by-ishrat-kaur-at-the-drawing-room-smoke-house-deli-iehpl/event",
    "startDate": "2025-01-29T19:00:00+0530",
    "endDate": "2025-01-29T21:00:00+05:30",
    "description": "If you're interested in a bar Takeover & a masterclass to learn to make Gin cocktails, mixologist Ishrat Kaur is hosting"
  },
  {
    "id": "buzz.venn:3489",
    "name": "Sound Meditation - New Moon",
    "image": "https://api.venn.buzz/rails/active_storage/blobs/redirect/eyJfcmFpbHMiOnsiZGF0YSI6MTU4NTQsInB1ciI6ImJsb2JfaWQifX0=--f938a20d0b9e726821459bace5f1e07d2e9e8291/9ef7f6f1-fc65-4d1e-aed2-9fbabd43b966",
    "location": {
      "name": "Red Brick Studio, Indiranagar",
      "address": "Red Brick Studio, Indiranagar Bangalore"
    },
    "url": "https://app.venn.buzz/social_experience/3489",
    "sameAs": "https://in.bookmyshow.com/events/sound-meditation-new-moon/ET00429868",
    "startDate": "2025-01-29T19:30:00+0530",
    "endDate": "2025-01-29T21:30:00+05:30",
    "description": "If you're interested in an intention setting, sound healing meditation with Tibetan bowls, gong & Vibrations, facilitator Tanmayi is hosting"
  },
  {
    "id": "buzz.venn:3490",
    "name": "The Thief Who Stole My Heart",
    "image": "https://api.venn.buzz/rails/active_storage/blobs/redirect/eyJfcmFpbHMiOnsiZGF0YSI6MTU4NTYsInB1ciI6ImJsb2JfaWQifX0=--303921212c7bcc986ccfaaa88d34a80e1f93f397/2fdadeff-36c2-4440-9bab-e229589c717f",
    "location": {
      "name": "BIC, Domlur",
      "address": "BIC, Domlur Bangalore"
    },
    "url": "https://app.venn.buzz/social_experience/3490",
    "sameAs": "https://bangaloreinternationalcentre.org/event/the-thief-who-stole-my-heart/",
    "startDate": "2025-01-29T18:30:00+0530",
    "endDate": "2025-01-29T20:30:00+05:30",
    "description": "A talk delving into the Chola dynasty's remarkable blend of devotion, artistry & resourcefulness with Prof. Vidya Dehejia"
  },
  {
    "id": "buzz.venn:3491",
    "name": "Unorthodox Calligraphy",
    "image": "https://api.venn.buzz/rails/active_storage/blobs/redirect/eyJfcmFpbHMiOnsiZGF0YSI6MTU4NTgsInB1ciI6ImJsb2JfaWQifX0=--a020ba10654466c3ed429edcc8ff773d64e17d60/6024b5f8-7d6e-400b-8ed0-ff087b62e624",
    "location": {
      "name": "PES University, BSK III Stage",
      "address": "PES University, BSK III Stage Bangalore"
    },
    "url": "https://app.venn.buzz/social_experience/3491",
    "sameAs": "https://www.instagram.com/p/DE9TiHLoNfc/",
    "startDate": "2025-01-29T10:00:00+0530",
    "endDate": "2025-01-29T12:00:00+05:30",
    "description": "If you're interested to learn freestyle calligraphy, artist Chinmay Hegde is hosting"
  }
]